AMDock/Docking_Program.py
AMDock/__init__.py
AMDock/_version.py
AMDock/checker.py
AMDock/command_runner.py
AMDock/file_loader.py
AMDock/info_tab.py
AMDock/input_tab.py
AMDock/lobby_tab.py
AMDock/log_window.py
AMDock/output_file.py
AMDock/qradialbar.py
AMDock/result2tab.py
AMDock/result_tab.py
AMDock/rfile_show.py
AMDock/setting_tab.py
AMDock/splash_screen.py
AMDock/tools.py
AMDock/variables.py
AMDock/warning.py
AMDock/data/AD4Zn.dat
AMDock/data/AutoLigand.py
AMDock/data/amdock_icon.png
AMDock/data/amdock_uninstall_icon.png
AMDock/data/autodock4
AMDock/data/autodock4_mac
AMDock/data/autogrid4
AMDock/data/autogrid4_mac
AMDock/data/back_icon.png
AMDock/data/configration.ini
AMDock/data/configuration.ini
AMDock/data/error_checker.png
AMDock/data/error_checker_ok.png
AMDock/data/grid_values.py
AMDock/data/home_icon.png
AMDock/data/home_icon_white.png
AMDock/data/jetbrains-variant-4.png
AMDock/data/ligand_site_pymol.py
AMDock/data/new_icon.png
AMDock/data/next_icon.png
AMDock/data/prepare_gpf4zn.py
AMDock/data/presentation.png
AMDock/data/protein_align_pymol.py
AMDock/data/reset.png
AMDock/data/splashscreen.png
AMDock/data/style.css
AMDock/data/vina
AMDock/data/vina_mac
AMDock/data/zinc_pseudo.py
AMDock-1.6.2.dist-info/LICENSE.txt
AMDock-1.6.2.dist-info/METADATA
AMDock-1.6.2.dist-info/WHEEL
AMDock-1.6.2.dist-info/entry_points.txt
AMDock-1.6.2.dist-info/top_level.txt
AMDock-1.6.2.dist-info/RECORD
