Metadata-Version: 2.1
Name: AMDock
Version: 1.6.2
Summary: AMDock: Assisted Molecular Docking with Autodock4 and Autodock Vina
Home-page: https://github.com/Valdes-Tresanco-MS/AMDock
Author: Mario S. Valdes-Tresanco and Mario E. Valdes-Tresanco 
Author-email: mariosergiovaldes145@gmail.com
Maintainer: Mario S. Valdes-Tresanco
Maintainer-email: mariosergiovaldes145@gmail.com
License: GPLv3
Keywords: AMDock,AutoDock Vina,AutoDock4,AutoDock4Zn,Docking
Platform: UNKNOWN
License-File: LICENSE.txt
Requires-Dist: PyQt5 (>=5.15.4)
